Makefile
README
distribute_setup.py
setup.py
bin/testosterone
doc/DESIGN
doc/RELEASE
doc/TODO
doc/icons/blank.gif
doc/icons/blank.png
doc/icons/contents.gif
doc/icons/contents.png
doc/icons/index.gif
doc/icons/index.png
doc/icons/modules.gif
doc/icons/modules.png
doc/icons/next.gif
doc/icons/next.png
doc/icons/previous.gif
doc/icons/previous.png
doc/icons/pyfav.gif
doc/icons/pyfav.png
doc/icons/up.gif
doc/icons/up.png
doc/icons/zeta.ico
doc/man1/testosterone.1
doc/tex/Makefile
doc/tex/interactive.tex
doc/tex/options.tex
doc/tex/scripted.tex
doc/tex/testosterone.tex
doc/tex/update.py
testosterone/__init__.py
testosterone.egg-info/PKG-INFO
testosterone.egg-info/SOURCES.txt
testosterone.egg-info/dependency_links.txt
testosterone.egg-info/entry_points.txt
testosterone.egg-info/top_level.txt
testosterone/cli/__init__.py
testosterone/cli/main.py
testosterone/cli/reporters.py
testosterone/cli/utils.py
testosterone/interactive/__init__.py
testosterone/interactive/detail.py
testosterone/interactive/summary.py
testosterone/interactive/utils.py
testosterone/interactive/screens/__init__.py
testosterone/interactive/screens/base.py
testosterone/interactive/screens/debugging.py
testosterone/interactive/screens/detail.py
testosterone/interactive/screens/error.py
testosterone/interactive/screens/summary.py
testosterone/tests/__init__.py
testosterone/tests/cli.py
testosterone/tests/demo.py
testosterone/tests/utils.py
testosterone/tests/interactive/__init__.py
testosterone/tests/interactive/marshallers.py
testosterone/tests/interactive/scrollarea.py