Metadata-Version: 1.0
Name: testosterone
Version: 0.4.2
Summary: testosterone is a manly testing interface for Python.
Home-page: http://www.zetadev.com/software/testosterone/
Author: Chad Whitacre
Author-email: chad@zetaweb.com
License: UNKNOWN
Platform: UNKNOWN
Classifier: Development Status :: 4 - Beta
Classifier: Environment :: Console
Classifier: Environment :: Console :: Curses
Classifier: Intended Audience :: Developers
Classifier: License :: Freeware
Classifier: Natural Language :: English
Classifier: Operating System :: MacOS :: MacOS X
Classifier: Operating System :: Microsoft :: Windows
Classifier: Operating System :: POSIX
Classifier: Programming Language :: Python
Classifier: Topic :: Software Development :: Testing
